elmes/__init__.py
elmes/agent.py
elmes/config.py
elmes/directions.py
elmes/entity.py
elmes/evaluation.py
elmes/model.py
elmes/router.py
elmes/run.py
elmes/utils.py
elmes/cli/main.py
elmes/cli/draw/__init__.py
elmes/cli/eval/__init__.py
elmes/cli/export/__init__.py
elmes/cli/export/json_.py
elmes/cli/export/label_studio.py
elmes/cli/export/const/label_studio.py
elmes/cli/export/exporter/json_.py
elmes/cli/export/exporter/label_studio_.py
elmes/cli/generate/__init__.py
elmes/cli/visualize/__init__.py
assets/fonts/sarasa-mono-sc-regular.ttf
elmes-0.1.13.dist-info/METADATA
elmes-0.1.13.dist-info/WHEEL
elmes-0.1.13.dist-info/entry_points.txt
elmes-0.1.13.dist-info/RECORD
