Metadata-Version: 2.4
Name: elmes
Version: 0.1.13
Summary: Education Language Model Evaluation System
Requires-Python: >=3.10
Requires-Dist: anthropic>=0.52.0
Requires-Dist: click>=8.2.1
Requires-Dist: grandalf>=0.8
Requires-Dist: langchain-openai>=0.3.18
Requires-Dist: langchain>=0.3.25
Requires-Dist: langgraph-checkpoint-sqlite>=2.0.10
Requires-Dist: langgraph>=0.4.7
Requires-Dist: matplotlib>=3.10.3
Requires-Dist: pandas>=2.2.3
Requires-Dist: polyfactory>=2.21.0
Requires-Dist: pyppeteer>=2.0.0
Requires-Dist: python-dotenv>=1.1.0
Requires-Dist: pyyaml>=6.0.2
Requires-Dist: requests>=2.32.3
Requires-Dist: tenacity>=9.1.2
